Project_files/lut3.v
module lut3(
    input wire [2:0] in,
    input wire [7:0] lut_contents_init,
    input wire load,
    output wire out

);
reg [7:0] lut_contents = 8'b00000000;

always@ (posedge load) //only happens when load is high, 
begin 
lut_contents <= lut_contents_init;
end


assign out = lut_contents[in];
endmodule

Project_files/lut3_tb.v
module lut3_tb;

reg [2:0] inputs;
reg [7:0] lut_contents_init;
reg load;
wire outee;

lut3 my_lut3 (
    .in(inputs),
    .lut_contents_init(lut_contents_init),
    .load(load),
    .out(outee)
);

initial begin
    $dumpfile("lut3_tb.vcd");
    $dumpvars(0, lut3_tb);

    //initialise values
    //lut_contents_init = 8'b10101010; 
    lut_contents_init = 8'b11011100;
    load = 1'b1; #10; 
    load = 1'b0; 

    inputs = 3'b000; #10;
    $display("Input: %b, Output: %b", inputs, outee);
    inputs = 3'b001; #10;
    $display("Input: %b, Output: %b", inputs, outee);
    inputs = 3'b010; #10;
    $display("Input: %b, Output: %b", inputs, outee);
    inputs = 3'b011; #10;
    $display("Input: %b, Output: %b", inputs, outee);
    inputs = 3'b100; #10;
    $display("Input: %b, Output: %b", inputs, outee);
    inputs = 3'b101; #10;
    $display("Input: %b, Output: %b", inputs, outee);
    inputs = 3'b110; #10;
    $display("Input: %b, Output: %b", inputs, outee);
    inputs = 3'b111; #10;
    $display("Input: %b, Output: %b", inputs, outee);

    $display("test complete");
end

endmodule

Project_files/lut3_tb.vcd
$date
	Mon Nov 27 12:59:59 2023
$end
$version
	Icarus Verilog
$end
$timescale
	1s
$end
$scope module lut3_tb $end
$var wire 1 ! outee $end
$var reg 3 " inputs [2:0] $end
$var reg 1 # load $end
$var reg 8 $ lut_contents_init [7:0] $end
$scope module my_lut3 $end
$var wire 3 % in [2:0] $end
$var wire 1 # load $end
$var wire 8 & lut_contents_init [7:0] $end
$var wire 1 ! out $end
$var reg 8 ' lut_contents [7:0] $end
$upscope $end
$upscope $end
$enddefinitions $end
$comment Show the parameter values. $end
$dumpall
$end
#0
$dumpvars
b11011100 '
b11011100 &
bx %
b11011100 $
1#
bx "
x!
$end
#10
0!
b0 "
b0 %
0#
#20
b1 "
b1 %
#30
1!
b10 "
b10 %
#40
b11 "
b11 %
#50
b100 "
b100 %
#60
0!
b101 "
b101 %
#70
1!
b110 "
b110 %
#80
b111 "
b111 %
